<?xml version="1.0" encoding="utf-8" ?>
<dwsync>
<file name="galerie_poz_blue.gif" server="krajicek.phorum.cz//" local="128921665840000000" remote="128922104400000000" />
<file name="list_poz.gif" server="krajicek.phorum.cz//" local="128921646800000000" remote="128922104400000000" />
<file name="list_poz.jpg" server="krajicek.phorum.cz//" local="128921629720000000" remote="128922104400000000" />
<file name="list_poz.png" server="krajicek.phorum.cz//" local="128921636580000000" remote="128922104400000000" />
<file name="barevna_rotace_pozad.png" server="krajicek.phorum.cz//" local="128924872360000000" remote="128925585000000000" />
<file name="barevnycas.png" server="krajicek.phorum.cz//" local="128924815960000000" remote="128925585000000000" />
<file name="barevnycasb.jpg" server="krajicek.phorum.cz//" local="128924815300000000" remote="128925585000000000" />
<file name="bludiste-copy.png" server="krajicek.phorum.cz//" local="128924835400000000" remote="128925585000000000" />
<file name="ledovy_vjejir_pozadi.png" server="krajicek.phorum.cz//" local="128924859260000000" remote="128925585000000000" />
<file name="obr1.png" server="krajicek.phorum.cz//" local="128924794700000000" remote="128925585000000000" />
<file name="obr2.png" server="krajicek.phorum.cz//" local="128924797620000000" remote="128925585000000000" />
<file name="pozadi_final.png" server="krajicek.phorum.cz//" local="128924882280000000" remote="128925585000000000" />
<file name="pozadi_zahlavi.psd" server="krajicek.phorum.cz//" local="128924968260000000" remote="128925585000000000" />
</dwsync>